imodels/__init__.py
imodels/rule_set/__init__.py
imodels/rule_set/rule_set.py
imodels/util/__init__.py
imodels/util/arguments.py
imodels/util/convert.py
imodels/util/extract.py
imodels/util/rule.py
imodels/util/score.py
imodels/util/transforms.py
rulefit_vvsu/__init__.py
rulefit_vvsu/main.py
rulefit_vvsu-0.2.2.dist-info/METADATA
rulefit_vvsu-0.2.2.dist-info/WHEEL
rulefit_vvsu-0.2.2.dist-info/RECORD
