Metadata-Version: 2.1
Name: rulefit-vvsu
Version: 0.2.2
Summary: 
Author: roman
Requires-Python: >=3.9,<4.0
Classifier: Programming Language :: Python :: 3
Classifier: Programming Language :: Python :: 3.9
Classifier: Programming Language :: Python :: 3.10
Classifier: Programming Language :: Python :: 3.11
Classifier: Programming Language :: Python :: 3.12
Requires-Dist: mlxtend (>=0.23.1,<0.24.0)
Requires-Dist: pandas (>=2.2.0)
Requires-Dist: scikit-learn (>=1.4.0)
